Metadata-Version: 1.0
Name: notifications
Version: 0.3.2
Summary: Client for the iOS app "Notifications" (aka "Push 4.0").
Home-page: https://github.com/cjlucas/notifications
Author: Chris Lucas
Author-email: chris@chrisjlucas.com
License: ISC
Platform: UNKNOWN
Classifier: Development Status :: 4 - Beta
Classifier: Intended Audience :: Developers
Classifier: Intended Audience :: End Users/Desktop
Classifier: Intended Audience :: System Administrators
Classifier: License :: OSI Approved :: BSD License
Classifier: Operating System :: OS Independent
Classifier: Programming Language :: Python :: 2
Classifier: Programming Language :: Python :: 3
Classifier: Topic :: Communications
Classifier: Topic :: Internet :: WWW/HTTP
